CHANGES.txt
MANIFEST.in
README.rst
setup.py
shogen.py
shogen.egg-info/PKG-INFO
shogen.egg-info/SOURCES.txt
shogen.egg-info/dependency_links.txt
shogen.egg-info/requires.txt
shogen.egg-info/top_level.txt
src/__init__.py
src/query.py
src/sbml.py
src/utils.py
src/encodings/convert.lp
src/encodings/convert_sds.lp
src/encodings/filter_couples.lp
src/encodings/preprocess.lp
src/encodings/sgs.lp