Metadata-Version: 1.0
Name: shogen
Version: 1.4.3
Summary: Finding shortest genome segments that regulate metabolic pathways.
Home-page: http://pypi.python.org/pypi/shogen/
Author: Sven Thiele
Author-email: sthiele78@gmail.com
License: GPLv3+
Platform: UNKNOWN
